[
    {
        "OrdemId": 1142256848,
        "ItemId": 45945254,
        "Material": "Material1",
        "Descricao": "Descricao1",
        "Quantidade": 184423464,
        "PrecoUni": 1211362257599.83,
        "PrecoTot": 3413326088339.09
    },
    {
        "OrdemId": 793723814,
        "ItemId": 689152889,
        "Material": "Material2",
        "Descricao": "Descricao2",
        "Quantidade": 629738593,
        "PrecoUni": 2113095736131.07,
        "PrecoTot": 9466184224002.06
    },
    {
        "OrdemId": 59714180,
        "ItemId": 1440254861,
        "Material": "Material3",
        "Descricao": "Descricao3",
        "Quantidade": 145371885,
        "PrecoUni": 6696286485530.43,
        "PrecoTot": 8069858017843.21
    },
    {
        "OrdemId": 948010573,
        "ItemId": 1077196316,
        "Material": "Material4",
        "Descricao": "Descricao4",
        "Quantidade": 1061570491,
        "PrecoUni": 2568802472669.63,
        "PrecoTot": 4048444407526.4
    },
    {
        "OrdemId": 144580108,
        "ItemId": 1256319225,
        "Material": "Material5",
        "Descricao": "Descricao5",
        "Quantidade": 2049461545,
        "PrecoUni": 1097470028325.91,
        "PrecoTot": 6615658854134.38
    },
    {
        "OrdemId": 1162013708,
        "ItemId": 925404963,
        "Material": "Material6",
        "Descricao": "Descricao6",
        "Quantidade": 1543465701,
        "PrecoUni": 6981145837344.22,
        "PrecoTot": 2579293397720.9
    },
    {
        "OrdemId": 218213080,
        "ItemId": 1501066526,
        "Material": "Material7",
        "Descricao": "Descricao7",
        "Quantidade": 2086579723,
        "PrecoUni": 1888670201878.99,
        "PrecoTot": 9359551265370.1
    },
    {
        "OrdemId": 873772849,
        "ItemId": 1290537512,
        "Material": "Material8",
        "Descricao": "Descricao8",
        "Quantidade": 783350370,
        "PrecoUni": 4864876354113.22,
        "PrecoTot": 8298771118279.54
    },
    {
        "OrdemId": 1879133954,
        "ItemId": 27961604,
        "Material": "Material9",
        "Descricao": "Descricao9",
        "Quantidade": 587683213,
        "PrecoUni": 593810500577.09,
        "PrecoTot": 4850651244632.9
    },
    {
        "OrdemId": 1726454479,
        "ItemId": 533145732,
        "Material": "Material10",
        "Descricao": "Descricao10",
        "Quantidade": 954079360,
        "PrecoUni": 9122446258552.37,
        "PrecoTot": 3035885354038.32
    },
    {
        "OrdemId": 980907091,
        "ItemId": 945245148,
        "Material": "Material11",
        "Descricao": "Descricao11",
        "Quantidade": 1412703825,
        "PrecoUni": 6834764846134.93,
        "PrecoTot": 9787371715065.09
    },
    {
        "OrdemId": 2034334858,
        "ItemId": 2114493533,
        "Material": "Material12",
        "Descricao": "Descricao12",
        "Quantidade": 952109025,
        "PrecoUni": 7071526653598.99,
        "PrecoTot": 1541833211667.83
    },
    {
        "OrdemId": 1638612021,
        "ItemId": 1180812677,
        "Material": "Material13",
        "Descricao": "Descricao13",
        "Quantidade": 1793923361,
        "PrecoUni": 1685497355647.38,
        "PrecoTot": 3648810025770.21
    },
    {
        "OrdemId": 1447889548,
        "ItemId": 266140497,
        "Material": "Material14",
        "Descricao": "Descricao14",
        "Quantidade": 1251837686,
        "PrecoUni": 772921871393.91,
        "PrecoTot": 287445655558.25
    },
    {
        "OrdemId": 406140868,
        "ItemId": 1723088180,
        "Material": "Material15",
        "Descricao": "Descricao15",
        "Quantidade": 2011565488,
        "PrecoUni": 8214097314048.55,
        "PrecoTot": 869731153361.49
    },
    {
        "OrdemId": 1337398587,
        "ItemId": 697678352,
        "Material": "Material16",
        "Descricao": "Descricao16",
        "Quantidade": 1333888425,
        "PrecoUni": 6464386342559.01,
        "PrecoTot": 9839541940018.53
    },
    {
        "OrdemId": 708705471,
        "ItemId": 461356246,
        "Material": "Material17",
        "Descricao": "Descricao17",
        "Quantidade": 1823465976,
        "PrecoUni": 5463053965941.07,
        "PrecoTot": 9125456803012.63
    },
    {
        "OrdemId": 826194855,
        "ItemId": 1293022898,
        "Material": "Material18",
        "Descricao": "Descricao18",
        "Quantidade": 57393991,
        "PrecoUni": 2402001162990.92,
        "PrecoTot": 9817885062657.29
    },
    {
        "OrdemId": 2049181887,
        "ItemId": 686466880,
        "Material": "Material19",
        "Descricao": "Descricao19",
        "Quantidade": 2127043332,
        "PrecoUni": 9320796257816.25,
        "PrecoTot": 6707324227318.16
    },
    {
        "OrdemId": 123076798,
        "ItemId": 1045594552,
        "Material": "Material20",
        "Descricao": "Descricao20",
        "Quantidade": 2045145821,
        "PrecoUni": 3505797679536.04,
        "PrecoTot": 1195984671358.01
    }
]